setup.cfg
setup.py
bootcamp/__init__.py
bootcamp/exceptions.py
bootcamp/trainer.py
bootcamp/utils.py
bootcamp.egg-info/PKG-INFO
bootcamp.egg-info/SOURCES.txt
bootcamp.egg-info/dependency_links.txt
bootcamp.egg-info/requires.txt
bootcamp.egg-info/top_level.txt
bootcamp.egg-info/zip-safe
bootcamp/agents/__init__.py
bootcamp/agents/agent.py
bootcamp/agents/reinforce.py
bootcamp/approximators/__init__.py
bootcamp/approximators/mlp.py
bootcamp/callbacks/__init__.py
bootcamp/callbacks/evaluate.py
bootcamp/callbacks/log.py
bootcamp/callbacks/monitor.py
bootcamp/metrics/__init__.py
bootcamp/metrics/average_return.py