Metadata-Version: 1.0
Name: bootcamp
Version: 0.1.0
Summary: Reinforcement learning with PyTorch and OpenAI Gym
Home-page: https://github.com/jasonkriss/bootcamp
Author: Jason Kriss
Author-email: jasonkriss@gmail.com
License: MIT
Platform: UNKNOWN
